financefunctions/__init__.py
financefunctions/dataframes.py
financefunctions/functions.py
financefunctions/series.py
financefunctions-0.0.2.4.dist-info/METADATA
financefunctions-0.0.2.4.dist-info/WHEEL
financefunctions-0.0.2.4.dist-info/top_level.txt
financefunctions-0.0.2.4.dist-info/RECORD
