Metadata-Version: 2.2
Name: financefunctions
Version: 0.0.2.4
Summary: a simple package that creates some convenience functions for financial data
Author-email: NeuralDevelopment <neutro2@outlook.de>
License: MIT License
Project-URL: Homepage, https://dev.azure.com/neuraldevelopment/financefunctions
Classifier: Programming Language :: Python :: 3
Classifier: License :: OSI Approved :: MIT License
Classifier: Operating System :: OS Independent
Classifier: Programming Language :: Python :: 3.10
Classifier: Programming Language :: Python :: 3.11
Classifier: Programming Language :: Python :: 3.12
Requires-Python: >=3.10
Requires-Dist: basefunctions>=0.4.3.2
Requires-Dist: pandas>=2.0
Requires-Dist: scipy>=1.13
Requires-Dist: statsmodels>=0.13
Provides-Extra: dev
Provides-Extra: test
